try_parse/__init__.py
try_parse/parse_tests.py
try_parse/utils.py
try_parse-0.0.9.dist-info/LICENSE
try_parse-0.0.9.dist-info/METADATA
try_parse-0.0.9.dist-info/WHEEL
try_parse-0.0.9.dist-info/top_level.txt
try_parse-0.0.9.dist-info/RECORD
