Metadata-Version: 2.1
Name: try-parse
Version: 0.0.9
Summary: Easily and safety cast objects to the desired data type
Home-page: https://github.com/agorinenko/try-parse
Author: Gorinenko Anton
Author-email: anton.gorinenko@gmail.com
License: UNKNOWN
Keywords: python,parse,cast
Platform: UNKNOWN
Classifier: Programming Language :: Python :: 3.7
Classifier: Programming Language :: Python :: 3.8
Classifier: License :: OSI Approved :: MIT License
Classifier: Operating System :: OS Independent
Requires-Python: >=3.7
